Crylearn/CGCNN_atom_emb.json
Crylearn/__init__.py
Crylearn/__pycache__/__init__.cpython-39.pyc
Crylearn/__pycache__/cry2graph.cpython-39.pyc
Crylearn-0.1.5.dist-info/METADATA
Crylearn-0.1.5.dist-info/WHEEL
Crylearn-0.1.5.dist-info/top_level.txt
Crylearn-0.1.5.dist-info/RECORD
